pytermwindows/ScrollWindow.py
pytermwindows/Window.py
pytermwindows/__init__.py
pytermwindows-0.0.5.dist-info/LICENSE
pytermwindows-0.0.5.dist-info/METADATA
pytermwindows-0.0.5.dist-info/WHEEL
pytermwindows-0.0.5.dist-info/top_level.txt
pytermwindows-0.0.5.dist-info/RECORD
