Metadata-Version: 2.1
Name: pytermwindows
Version: 0.0.5
Summary: A package to generate responsive terminal windows in Python
Home-page: https://github.com/NoahHenrikKleinschmidt/PyTermWindows
Author: Noah H. Kleinschmidt
Author-email: noah.kleinschmidt@students.unibe.ch
Classifier: Programming Language :: Python :: 3
Classifier: License :: OSI Approved :: GNU General Public License v3 (GPLv3)
Classifier: Operating System :: OS Independent
Requires-Python: >=3.6
License-File: LICENSE
